Metadata-Version: 1.1
Name: test-packages
Version: 1.0.1
Summary: this is a test for package by myself upload to pypi
Home-page: https://github.com/lichanghong/wenyali.git
Author: poison
Author-email: 948815501@qq.com
License: UNKNOWN
Keywords: keyword
Platform: UNKNOWN
Classifier: License :: OSI Approved :: MIT License
Classifier: Programming Language :: Python
Classifier: Intended Audience :: Developers
Classifier: Operating System :: OS Independent
